bisect.py
setup.py
micropython_bisect.egg-info/PKG-INFO
micropython_bisect.egg-info/SOURCES.txt
micropython_bisect.egg-info/dependency_links.txt
micropython_bisect.egg-info/top_level.txt