Metadata-Version: 1.0
Name: micropython-bisect
Version: 0.5
Summary: CPython bisect module ported to MicroPython
Home-page: https://github.com/micropython/micropython/issues/405
Author: MicroPython Developers
Author-email: micro-python@googlegroups.com
License: Python
Platform: UNKNOWN
